divide_char_type.py
divide_char_type-0.2.9.dist-info/METADATA
divide_char_type-0.2.9.dist-info/WHEEL
divide_char_type-0.2.9.dist-info/top_level.txt
divide_char_type-0.2.9.dist-info/RECORD
