Metadata-Version: 2.1
Name: divide-char-type
Version: 0.2.9
Summary: Divide documents by character type
Home-page: https://github.com/ShinyaAkagiI/divide_character_type
Author: Shinya Akagi
License: PSF
Platform: UNKNOWN
